c2go/__init__.py
c2go/__main__.py
c2go/_verison.py
c2go/_version.py
c2go-0.2.3.dist-info/DESCRIPTION.rst
c2go-0.2.3.dist-info/METADATA
c2go-0.2.3.dist-info/RECORD
c2go-0.2.3.dist-info/WHEEL
c2go-0.2.3.dist-info/entry_points.txt
c2go-0.2.3.dist-info/metadata.json
c2go-0.2.3.dist-info/top_level.txt
