Metadata-Version: 2.0
Name: c2go
Version: 0.2.3
Summary: c to go conversion
Home-page: https://github.com/xoviat/c2go
Author: Mars Galactic
Author-email: xoviat@users.noreply.github.com
License: Copyright (c) 2011, Alexander RÃ¸dseth
Platform: any
Requires-Dist: pycparser
